Metadata-Version: 2.1
Name: SkSchedule
Version: 0.0.2
Summary: 为生科查课提供便利
Home-page: https://gitee.com/huang-hongzhe/sk-schedule.git
Author: ali
Author-email: 2528104776@qq.com
License: MIT
Platform: UNKNOWN
